botamino/__init__.py
botamino/bot_amino.py
aminobot-0.1.1.dist-info/METADATA
aminobot-0.1.1.dist-info/WHEEL
aminobot-0.1.1.dist-info/top_level.txt
aminobot-0.1.1.dist-info/RECORD
