Metadata-Version: 2.4
Name: aminobot
Version: 0.1.1
Home-page: 
Author: DarkCat
Author-email: 
Classifier: Programming Language :: Python :: 3
Classifier: License :: OSI Approved :: MIT License
Classifier: Operating System :: OS Independent
Requires-Python: >=3.6
Requires-Dist: requests>=2.0.0
Dynamic: author
Dynamic: classifier
Dynamic: requires-dist
Dynamic: requires-python
